{
"data":[
{"timestamp": "1365466854", "value":
{"count": 7353}},
{"timestamp": "1351602556", "value":
{"count": 7287}},
{"timestamp": "1363035304", "value":
{"count": 6943}},
{"timestamp": "1352562807", "value":
{"count": 6397}},
{"timestamp": "1349647521", "value":
{"count": 5838}},
{"timestamp": "1362286842", "value":
{"count": 5683}},
{"timestamp": "1356651733", "value":
{"count": 5498}},
{"timestamp": "1343670740", "value":
{"count": 5253}},
{"timestamp": "1348169990", "value":
{"count": 5163}},
{"timestamp": "1352712352", "value":
{"count": 4955}},
{"timestamp": "1344094541", "value":
{"count": 4926}},
{"timestamp": "1357579201", "value":
{"count": 4859}},
{"timestamp": "1348493159", "value":
{"count": 4773}},
{"timestamp": "1365447472", "value":
{"count": 4730}},
{"timestamp": "1351738947", "value":
{"count": 4592}},
{"timestamp": "1370652275", "value":
{"count": 4591}},
{"timestamp": "1352907731", "value":
{"count": 4498}},
{"timestamp": "1356121895", "value":
{"count": 4492}},
{"timestamp": "1346750476", "value":
{"count": 4450}},
{"timestamp": "1352201126", "value":
{"count": 4445}},
{"timestamp": "1344612062", "value":
{"count": 4401}},
{"timestamp": "1350542412", "value":
{"count": 4395}},
{"timestamp": "1356295618", "value":
{"count": 4400}},
{"timestamp": "1362749334", "value":
{"count": 4155}},
{"timestamp": "1344209549", "value":
{"count": 4130}},
{"timestamp": "1351310508", "value":
{"count": 4125}},
{"timestamp": "1350225319", "value":
{"count": 4082}},
{"timestamp": "1355993372", "value":
{"count": 4060}},
{"timestamp": "1366994919", "value":
{"count": 3988}},
{"timestamp": "1356406949", "value":
{"count": 3965}},
{"timestamp": "1354098266", "value":
{"count": 3904}},
{"timestamp": "1355673730", "value":
{"count": 3897}},
{"timestamp": "1348013453", "value":
{"count": 3898}},
{"timestamp": "1350571919", "value":
{"count": 3892}},
{"timestamp": "1356484031", "value":
{"count": 3867}},
{"timestamp": "1355245396", "value":
{"count": 3865}},
{"timestamp": "1358532677", "value":
{"count": 3843}},
{"timestamp": "1354980451", "value":
{"count": 3836}},
{"timestamp": "1348361307", "value":
{"count": 3819}},
{"timestamp": "1353267241", "value":
{"count": 3763}},
{"timestamp": "1354758930", "value":
{"count": 3744}},
{"timestamp": "1341271488", "value":
{"count": 3711}},
{"timestamp": "1355937358", "value":
{"count": 3677}},
{"timestamp": "1355355455", "value":
{"count": 3677}},
{"timestamp": "1371242745", "value":
{"count": 3660}},
{"timestamp": "1372089546", "value":
{"count": 3608}},
{"timestamp": "1354731724", "value":
{"count": 3577}},
{"timestamp": "1376481216", "value":
{"count": 3554}},
{"timestamp": "1362913656", "value":
{"count": 3517}},
{"timestamp": "1365808739", "value":
{"count": 3490}},
{"timestamp": "1361824745", "value":
{"count": 3482}},
{"timestamp": "1373502112", "value":
{"count": 3476}},
{"timestamp": "1366250147", "value":
{"count": 3470}},
{"timestamp": "1349206929", "value":
{"count": 3472}},
{"timestamp": "1354550881", "value":
{"count": 3433}},
{"timestamp": "1352316434", "value":
{"count": 3430}},
{"timestamp": "1358378721", "value":
{"count": 3429}},
{"timestamp": "1347558301", "value":
{"count": 3418}},
{"timestamp": "1352604643", "value":
{"count": 3416}},
{"timestamp": "1364151577", "value":
{"count": 3391}},
{"timestamp": "1360013864", "value":
{"count": 3392}},
{"timestamp": "1363132196", "value":
{"count": 3386}},
{"timestamp": "1344348930", "value":
{"count": 3353}},
{"timestamp": "1353001465", "value":
{"count": 3338}},
{"timestamp": "1374383162", "value":
{"count": 3323}},
{"timestamp": "1362247556", "value":
{"count": 3312}},
{"timestamp": "1351355586", "value":
{"count": 3313}},
{"timestamp": "1374689497", "value":
{"count": 3297}},
{"timestamp": "1369510045", "value":
{"count": 3292}},
{"timestamp": "1358383085", "value":
{"count": 3278}},
{"timestamp": "1375567064", "value":
{"count": 3268}},
{"timestamp": "1342884375", "value":
{"count": 3265}},
{"timestamp": "1358057088", "value":
{"count": 3243}},
{"timestamp": "1370527808", "value":
{"count": 3219}},
{"timestamp": "1372704114", "value":
{"count": 3218}},
{"timestamp": "1354437087", "value":
{"count": 3210}},
{"timestamp": "1370283143", "value":
{"count": 3211}},
{"timestamp": "1365163221", "value":
{"count": 3199}},
{"timestamp": "1374545446", "value":
{"count": 3191}},
{"timestamp": "1353088956", "value":
{"count": 3194}},
{"timestamp": "1367370178", "value":
{"count": 3187}},
{"timestamp": "1373423097", "value":
{"count": 3173}},
{"timestamp": "1355623859", "value":
{"count": 3168}},
{"timestamp": "1375248577", "value":
{"count": 3170}},
{"timestamp": "1360439213", "value":
{"count": 3170}},
{"timestamp": "1371574785", "value":
{"count": 3156}},
{"timestamp": "1372394168", "value":
{"count": 3157}},
{"timestamp": "1357787071", "value":
{"count": 3155}},
{"timestamp": "1375114281", "value":
{"count": 3140}},
{"timestamp": "1362652348", "value":
{"count": 3145}},
{"timestamp": "1360948181", "value":
{"count": 3139}},
{"timestamp": "1373135947", "value":
{"count": 3130}},
{"timestamp": "1365334664", "value":
{"count": 3118}},
{"timestamp": "1368481565", "value":
{"count": 3110}},
{"timestamp": "1365339267", "value":
{"count": 3099}},
{"timestamp": "1364509571", "value":
{"count": 3105}},
{"timestamp": "1373677633", "value":
{"count": 3099}},
{"timestamp": "1348233887", "value":
{"count": 3100}},
{"timestamp": "1365002057", "value":
{"count": 3089}},
{"timestamp": "1355695545", "value":
{"count": 3097}},
{"timestamp": "1348105013", "value":
{"count": 3087}},
{"timestamp": "1353932664", "value":
{"count": 3079}},
{"timestamp": "1345656194", "value":
{"count": 3075}},
{"timestamp": "1354213719", "value":
{"count": 3060}},
{"timestamp": "1376510424", "value":
{"count": 3062}},
{"timestamp": "1352653773", "value":
{"count": 3052}},
{"timestamp": "1367169026", "value":
{"count": 3060}},
{"timestamp": "1364586191", "value":
{"count": 3061}},
{"timestamp": "1364254805", "value":
{"count": 3049}},
{"timestamp": "1350762911", "value":
{"count": 3038}},
{"timestamp": "1366149563", "value":
{"count": 3035}},
{"timestamp": "1353508467", "value":
{"count": 3032}},
{"timestamp": "1352234999", "value":
{"count": 3022}},
{"timestamp": "1363043088", "value":
{"count": 3023}},
{"timestamp": "1354801642", "value":
{"count": 3021}},
{"timestamp": "1360171938", "value":
{"count": 3016}},
{"timestamp": "1352039164", "value":
{"count": 3005}},
{"timestamp": "1352652873", "value":
{"count": 3012}},
{"timestamp": "1355267919", "value":
{"count": 3000}},
{"timestamp": "1368886146", "value":
{"count": 2999}},
{"timestamp": "1373738600", "value":
{"count": 2985}},
{"timestamp": "1375446726", "value":
{"count": 2978}},
{"timestamp": "1367099913", "value":
{"count": 2976}},
{"timestamp": "1375828188", "value":
{"count": 2974}},
{"timestamp": "1376592034", "value":
{"count": 3121}},
{"timestamp": "1376059756", "value":
{"count": 2950}},
{"timestamp": "1354827314", "value":
{"count": 2951}},
{"timestamp": "1373934018", "value":
{"count": 2942}},
{"timestamp": "1369248081", "value":
{"count": 2944}},
{"timestamp": "1355067631", "value":
{"count": 2947}},
{"timestamp": "1374762854", "value":
{"count": 2943}},
{"timestamp": "1372325190", "value":
{"count": 2941}},
{"timestamp": "1366044061", "value":
{"count": 2933}},
{"timestamp": "1356751529", "value":
{"count": 2926}},
{"timestamp": "1355793020", "value":
{"count": 2920}},
{"timestamp": "1360763345", "value":
{"count": 2920}},
{"timestamp": "1366078480", "value":
{"count": 2913}},
{"timestamp": "1372807858", "value":
{"count": 2922}},
{"timestamp": "1352747959", "value":
{"count": 2911}},
{"timestamp": "1359044277", "value":
{"count": 2914}},
{"timestamp": "1373307731", "value":
{"count": 2910}},
{"timestamp": "1367589594", "value":
{"count": 2904}},
{"timestamp": "1360104431", "value":
{"count": 2904}},
{"timestamp": "1371929538", "value":
{"count": 2901}},
{"timestamp": "1375202041", "value":
{"count": 2897}},
{"timestamp": "1364702889", "value":
{"count": 2899}},
{"timestamp": "1360606075", "value":
{"count": 2893}},
{"timestamp": "1361019983", "value":
{"count": 2890}},
{"timestamp": "1370099627", "value":
{"count": 2890}},
{"timestamp": "1362440134", "value":
{"count": 2886}},
{"timestamp": "1365691758", "value":
{"count": 2876}},
{"timestamp": "1375709900", "value":
{"count": 2872}},
{"timestamp": "1371421312", "value":
{"count": 2879}},
{"timestamp": "1348990281", "value":
{"count": 2872}},
{"timestamp": "1355156921", "value":
{"count": 2868}},
{"timestamp": "1359634575", "value":
{"count": 2857}},
{"timestamp": "1355016782", "value":
{"count": 2853}},
{"timestamp": "1358432482", "value":
{"count": 2858}},
{"timestamp": "1368030699", "value":
{"count": 2839}},
{"timestamp": "1372656960", "value":
{"count": 2841}},
{"timestamp": "1369758108", "value":
{"count": 2837}},
{"timestamp": "1373052350", "value":
{"count": 2839}},
{"timestamp": "1368650159", "value":
{"count": 2836}},
{"timestamp": "1372539064", "value":
{"count": 2821}},
{"timestamp": "1357679289", "value":
{"count": 2824}},
{"timestamp": "1346243240", "value":
{"count": 2824}},
{"timestamp": "1371854403", "value":
{"count": 2817}},
{"timestamp": "1375885474", "value":
{"count": 2815}},
{"timestamp": "1369789139", "value":
{"count": 2820}},
{"timestamp": "1374433793", "value":
{"count": 2806}},
{"timestamp": "1354633441", "value":
{"count": 2807}},
{"timestamp": "1350024343", "value":
{"count": 2808}},
{"timestamp": "1365946018", "value":
{"count": 2800}},
{"timestamp": "1375787620", "value":
{"count": 2801}},
{"timestamp": "1361877773", "value":
{"count": 2803}},
{"timestamp": "1374510133", "value":
{"count": 2797}},
{"timestamp": "1374412315", "value":
{"count": 2792}},
{"timestamp": "1367953235", "value":
{"count": 2791}},
{"timestamp": "1367309837", "value":
{"count": 2782}},
{"timestamp": "1362856574", "value":
{"count": 2779}},
{"timestamp": "1364733934", "value":
{"count": 2778}},
{"timestamp": "1374856453", "value":
{"count": 2776}},
{"timestamp": "1369753631", "value":
{"count": 2773}},
{"timestamp": "1353998856", "value":
{"count": 2775}},
{"timestamp": "1362497422", "value":
{"count": 2779}},
{"timestamp": "1359141610", "value":
{"count": 2770}},
{"timestamp": "1362669505", "value":
{"count": 2763}},
{"timestamp": "1375655568", "value":
{"count": 2765}},
{"timestamp": "1347218983", "value":
{"count": 2761}},
{"timestamp": "1374242543", "value":
{"count": 2752}},
{"timestamp": "1349888723", "value":
{"count": 2755}},
{"timestamp": "1367553717", "value":
{"count": 2751}},
{"timestamp": "1359821376", "value":
{"count": 2753}},
{"timestamp": "1364566023", "value":
{"count": 2749}},
{"timestamp": "1358962444", "value":
{"count": 2748}},
{"timestamp": "1376000822", "value":
{"count": 2747}},
{"timestamp": "1376188609", "value":
{"count": 2749}},
{"timestamp": "1370564099", "value":
{"count": 2741}},
{"timestamp": "1359348066", "value":
{"count": 2747}},
{"timestamp": "1373979166", "value":
{"count": 2742}},
{"timestamp": "1373765931", "value":
{"count": 2746}},
{"timestamp": "1368744043", "value":
{"count": 2747}},
{"timestamp": "1350581303", "value":
{"count": 2741}},
{"timestamp": "1362260606", "value":
{"count": 2735}},
{"timestamp": "1352830122", "value":
{"count": 2739}},
{"timestamp": "1368589408", "value":
{"count": 2730}},
{"timestamp": "1371038027", "value":
{"count": 2725}},
{"timestamp": "1362073151", "value":
{"count": 2733}},
{"timestamp": "1361567738", "value":
{"count": 2734}},
{"timestamp": "1372462071", "value":
{"count": 2726}},
{"timestamp": "1374739032", "value":
{"count": 2727}},
{"timestamp": "1368058549", "value":
{"count": 2730}},
{"timestamp": "1356459783", "value":
{"count": 2720}},
{"timestamp": "1367770646", "value":
{"count": 2721}},
{"timestamp": "1373824004", "value":
{"count": 2720}},
{"timestamp": "1371464393", "value":
{"count": 2723}},
{"timestamp": "1360537230", "value":
{"count": 2720}},
{"timestamp": "1372355509", "value":
{"count": 2722}},
{"timestamp": "1368054786", "value":
{"count": 2713}},
{"timestamp": "1374304814", "value":
{"count": 2712}},
{"timestamp": "1365894883", "value":
{"count": 2705}},
{"timestamp": "1359566720", "value":
{"count": 2708}},
{"timestamp": "1342011536", "value":
{"count": 2705}},
{"timestamp": "1371645103", "value":
{"count": 2711}},
{"timestamp": "1370903949", "value":
{"count": 2708}},
{"timestamp": "1376353929", "value":
{"count": 2713}},
{"timestamp": "1374482527", "value":
{"count": 2709}},
{"timestamp": "1354739976", "value":
{"count": 2712}},
{"timestamp": "1372275781", "value":
{"count": 2700}},
{"timestamp": "1376549096", "value":
{"count": 2703}},
{"timestamp": "1364125380", "value":
{"count": 2694}},
{"timestamp": "1369666179", "value":
{"count": 2696}},
{"timestamp": "1368802979", "value":
{"count": 2696}},
{"timestamp": "1365129498", "value":
{"count": 2693}},
{"timestamp": "1372511927", "value":
{"count": 2689}},
{"timestamp": "1372737067", "value":
{"count": 2687}},
{"timestamp": "1372169942", "value":
{"count": 2688}},
{"timestamp": "1375090482", "value":
{"count": 2687}},
{"timestamp": "1367722344", "value":
{"count": 2683}},
{"timestamp": "1367245114", "value":
{"count": 2683}},
{"timestamp": "1373067672", "value":
{"count": 2685}},
{"timestamp": "1373463854", "value":
{"count": 2676}},
{"timestamp": "1345733108", "value":
{"count": 2674}},
{"timestamp": "1374012319", "value":
{"count": 2679}},
{"timestamp": "1355101170", "value":
{"count": 2670}},
{"timestamp": "1355739145", "value":
{"count": 2667}},
{"timestamp": "1372598626", "value":
{"count": 2667}},
{"timestamp": "1368532326", "value":
{"count": 2670}},
{"timestamp": "1363623871", "value":
{"count": 2668}},
{"timestamp": "1375394694", "value":
{"count": 2661}},
{"timestamp": "1370049572", "value":
{"count": 2667}},
{"timestamp": "1369238823", "value":
{"count": 2659}},
{"timestamp": "1364863083", "value":
{"count": 2659}},
{"timestamp": "1353864293", "value":
{"count": 2659}},
{"timestamp": "1353798929", "value":
{"count": 2657}},
{"timestamp": "1368552804", "value":
{"count": 2656}},
{"timestamp": "1366466141", "value":
{"count": 2654}},
{"timestamp": "1357181577", "value":
{"count": 2662}},
{"timestamp": "1375198762", "value":
{"count": 2661}},
{"timestamp": "1357230061", "value":
{"count": 2654}},
{"timestamp": "1353458622", "value":
{"count": 2654}},
{"timestamp": "1373559271", "value":
{"count": 2652}},
{"timestamp": "1363701224", "value":
{"count": 2650}},
{"timestamp": "1346426945", "value":
{"count": 2650}},
{"timestamp": "1375361531", "value":
{"count": 2653}},
{"timestamp": "1376150696", "value":
{"count": 2647}},
{"timestamp": "1344537448", "value":
{"count": 2648}},
{"timestamp": "1366324751", "value":
{"count": 2648}},
{"timestamp": "1372020297", "value":
{"count": 2648}},
{"timestamp": "1373221764", "value":
{"count": 2649}},
{"timestamp": "1360689580", "value":
{"count": 2638}},
{"timestamp": "1374810959", "value":
{"count": 2636}},
{"timestamp": "1369703661", "value":
{"count": 2634}},
{"timestamp": "1366725141", "value":
{"count": 2636}},
{"timestamp": "1370862836", "value":
{"count": 2629}},
{"timestamp": "1371604744", "value":
{"count": 2629}},
{"timestamp": "1368126711", "value":
{"count": 2625}},
{"timestamp": "1349534090", "value":
{"count": 2630}},
{"timestamp": "1365198197", "value":
{"count": 2625}},
{"timestamp": "1368371996", "value":
{"count": 2624}},
{"timestamp": "1350500777", "value":
{"count": 2625}},
{"timestamp": "1366791789", "value":
{"count": 2621}},
{"timestamp": "1360802481", "value":
{"count": 2630}},
{"timestamp": "1374934731", "value":
{"count": 2617}},
{"timestamp": "1369069872", "value":
{"count": 2618}},
{"timestamp": "1363964269", "value":
{"count": 2613}},
{"timestamp": "1369485060", "value":
{"count": 2616}},
{"timestamp": "1361395958", "value":
{"count": 2615}},
{"timestamp": "1352382949", "value":
{"count": 2620}},
{"timestamp": "1370180807", "value":
{"count": 2612}},
{"timestamp": "1366122335", "value":
{"count": 2616}},
{"timestamp": "1371755444", "value":
{"count": 2610}},
{"timestamp": "1373901153", "value":
{"count": 2613}},
{"timestamp": "1372625254", "value":
{"count": 2604}},
{"timestamp": "1347913111", "value":
{"count": 2608}},
{"timestamp": "1360188318", "value":
{"count": 2601}},
{"timestamp": "1354596394", "value":
{"count": 2603}},
{"timestamp": "1373906186", "value":
{"count": 2601}},
{"timestamp": "1372161087", "value":
{"count": 2597}},
{"timestamp": "1357254602", "value":
{"count": 2594}},
{"timestamp": "1370391159", "value":
{"count": 2602}},
{"timestamp": "1357054152", "value":
{"count": 2597}},
{"timestamp": "1370611278", "value":
{"count": 2597}},
{"timestamp": "1361034886", "value":
{"count": 2594}},
{"timestamp": "1355520183", "value":
{"count": 2594}},
{"timestamp": "1363121824", "value":
{"count": 2592}},
{"timestamp": "1372203067", "value":
{"count": 2598}},
{"timestamp": "1364246461", "value":
{"count": 2587}},
{"timestamp": "1360511814", "value":
{"count": 2589}},
{"timestamp": "1368946268", "value":
{"count": 2587}},
{"timestamp": "1357755932", "value":
{"count": 2585}},
{"timestamp": "1357696754", "value":
{"count": 2588}},
{"timestamp": "1359207838", "value":
{"count": 2580}},
{"timestamp": "1359654530", "value":
{"count": 2583}},
{"timestamp": "1366214281", "value":
{"count": 2579}},
{"timestamp": "1352082328", "value":
{"count": 2581}},
{"timestamp": "1372850954", "value":
{"count": 2575}},
{"timestamp": "1355932786", "value":
{"count": 2577}},
{"timestamp": "1365349580", "value":
{"count": 2574}},
{"timestamp": "1363788500", "value":
{"count": 2570}},
{"timestamp": "1357973385", "value":
{"count": 2569}},
{"timestamp": "1347865022", "value":
{"count": 2576}},
{"timestamp": "1369362223", "value":
{"count": 2571}},
{"timestamp": "1370134947", "value":
{"count": 2571}},
{"timestamp": "1371989406", "value":
{"count": 2572}},
{"timestamp": "1370468298", "value":
{"count": 2571}},
{"timestamp": "1354640323", "value":
{"count": 2567}},
{"timestamp": "1354898700", "value":
{"count": 2560}},
{"timestamp": "1372701604", "value":
{"count": 2559}},
{"timestamp": "1371129652", "value":
{"count": 2563}},
{"timestamp": "1373192502", "value":
{"count": 2557}},
{"timestamp": "1358020304", "value":
{"count": 2556}},
{"timestamp": "1369984480", "value":
{"count": 2563}},
{"timestamp": "1367931109", "value":
{"count": 2559}},
{"timestamp": "1370970348", "value":
{"count": 2554}},
{"timestamp": "1362595200", "value":
{"count": 2560}},
{"timestamp": "1375288162", "value":
{"count": 2552}},
{"timestamp": "1371290151", "value":
{"count": 2556}},
{"timestamp": "1362168585", "value":
{"count": 2557}},
{"timestamp": "1367725342", "value":
{"count": 2553}},
{"timestamp": "1367345880", "value":
{"count": 2559}},
{"timestamp": "1358724430", "value":
{"count": 2556}},
{"timestamp": "1372548385", "value":
{"count": 2554}},
{"timestamp": "1364343662", "value":
{"count": 2552}},
{"timestamp": "1376100530", "value":
{"count": 2554}},
{"timestamp": "1372393414", "value":
{"count": 2548}},
{"timestamp": "1355185561", "value":
{"count": 2548}},
{"timestamp": "1361618432", "value":
{"count": 2541}},
{"timestamp": "1370105243", "value":
{"count": 2540}},
{"timestamp": "1375546854", "value":
{"count": 2545}},
{"timestamp": "1364936749", "value":
{"count": 2544}},
{"timestamp": "1370463831", "value":
{"count": 2536}},
{"timestamp": "1369499127", "value":
{"count": 2535}},
{"timestamp": "1347818045", "value":
{"count": 2533}},
{"timestamp": "1375815485", "value":
{"count": 2534}},
{"timestamp": "1365776464", "value":
{"count": 2531}},
{"timestamp": "1374761205", "value":
{"count": 2534}},
{"timestamp": "1369762124", "value":
{"count": 2527}},
{"timestamp": "1359340744", "value":
{"count": 2529}},
{"timestamp": "1374627160", "value":
{"count": 2522}},
{"timestamp": "1370181330", "value":
{"count": 2528}},
{"timestamp": "1369880922", "value":
{"count": 2529}},
{"timestamp": "1357397648", "value":
{"count": 2523}},
{"timestamp": "1376387305", "value":
{"count": 2523}},
{"timestamp": "1371827836", "value":
{"count": 2525}},
{"timestamp": "1362950293", "value":
{"count": 2514}},
{"timestamp": "1374060191", "value":
{"count": 2522}},
{"timestamp": "1369619783", "value":
{"count": 2519}},
{"timestamp": "1369269384", "value":
{"count": 2521}},
{"timestamp": "1371149746", "value":
{"count": 2512}},
{"timestamp": "1370372840", "value":
{"count": 2508}},
{"timestamp": "1374117868", "value":
{"count": 2512}},
{"timestamp": "1376440942", "value":
{"count": 2509}},
{"timestamp": "1358905724", "value":
{"count": 2505}},
{"timestamp": "1372262562", "value":
{"count": 2505}},
{"timestamp": "1368969697", "value":
{"count": 2505}},
{"timestamp": "1365636248", "value":
{"count": 2507}},
{"timestamp": "1354910298", "value":
{"count": 2501}},
{"timestamp": "1371883280", "value":
{"count": 2505}},
{"timestamp": "1351096526", "value":
{"count": 2498}},
{"timestamp": "1369398265", "value":
{"count": 2503}},
{"timestamp": "1353062440", "value":
{"count": 2495}},
{"timestamp": "1361738682", "value":
{"count": 2494}},
{"timestamp": "1372213397", "value":
{"count": 2501}},
{"timestamp": "1366505376", "value":
{"count": 2495}},
{"timestamp": "1371435204", "value":
{"count": 2494}},
{"timestamp": "1376259906", "value":
{"count": 2496}},
{"timestamp": "1358211815", "value":
{"count": 2486}},
{"timestamp": "1366494628", "value":
{"count": 2485}},
{"timestamp": "1350509952", "value":
{"count": 2490}},
{"timestamp": "1358128973", "value":
{"count": 2484}},
{"timestamp": "1355528626", "value":
{"count": 2487}},
{"timestamp": "1362340168", "value":
{"count": 2482}},
{"timestamp": "1368173447", "value":
{"count": 2480}},
{"timestamp": "1367152323", "value":
{"count": 2477}},
{"timestamp": "1357080574", "value":
{"count": 2484}},
{"timestamp": "1356621873", "value":
{"count": 2476}},
{"timestamp": "1370724333", "value":
{"count": 2473}},
{"timestamp": "1372220479", "value":
{"count": 2476}},
{"timestamp": "1366382353", "value":
{"count": 2473}},
{"timestamp": "1362241647", "value":
{"count": 2472}},
{"timestamp": "1374271250", "value":
{"count": 2468}},
{"timestamp": "1376322439", "value":
{"count": 2464}},
{"timestamp": "1375840009", "value":
{"count": 2463}},
{"timestamp": "1366824005", "value":
{"count": 2463}},
{"timestamp": "1353782335", "value":
{"count": 2465}},
{"timestamp": "1359404496", "value":
{"count": 2461}},
{"timestamp": "1364755676", "value":
{"count": 2460}},
{"timestamp": "1373584151", "value":
{"count": 2458}},
{"timestamp": "1371686969", "value":
{"count": 2457}},
{"timestamp": "1355273463", "value":
{"count": 2460}},
{"timestamp": "1361909426", "value":
{"count": 2461}},
{"timestamp": "1370783605", "value":
{"count": 2454}},
{"timestamp": "1370362348", "value":
{"count": 2450}},
{"timestamp": "1359255669", "value":
{"count": 2446}},
{"timestamp": "1359306926", "value":
{"count": 2445}},
{"timestamp": "1367867849", "value":
{"count": 2445}},
{"timestamp": "1373391671", "value":
{"count": 2449}},
{"timestamp": "1364636271", "value":
{"count": 2447}},
{"timestamp": "1363389788", "value":
{"count": 2445}},
{"timestamp": "1366288034", "value":
{"count": 2444}},
{"timestamp": "1354039419", "value":
{"count": 2444}},
{"timestamp": "1365973694", "value":
{"count": 2450}},
{"timestamp": "1366643044", "value":
{"count": 2445}},
{"timestamp": "1350674953", "value":
{"count": 2439}},
{"timestamp": "1358624918", "value":
{"count": 2435}},
{"timestamp": "1358569534", "value":
{"count": 2441}},
{"timestamp": "1352666899", "value":
{"count": 2442}},
{"timestamp": "1373882391", "value":
{"count": 2429}},
{"timestamp": "1371178624", "value":
{"count": 2432}},
{"timestamp": "1362526128", "value":
{"count": 2432}},
{"timestamp": "1352420599", "value":
{"count": 2430}},
{"timestamp": "1353237608", "value":
{"count": 2424}},
{"timestamp": "1360264170", "value":
{"count": 2422}},
{"timestamp": "1353421984", "value":
{"count": 2424}},
{"timestamp": "1370822326", "value":
{"count": 2426}},
{"timestamp": "1370006070", "value":
{"count": 2420}},
{"timestamp": "1348075617", "value":
{"count": 2419}},
{"timestamp": "1372087984", "value":
{"count": 2417}},
{"timestamp": "1367190646", "value":
{"count": 2421}},
{"timestamp": "1357428849", "value":
{"count": 2415}},
{"timestamp": "1369459327", "value":
{"count": 2412}},
{"timestamp": "1361422848", "value":
{"count": 2407}},
{"timestamp": "1374209212", "value":
{"count": 2414}},
{"timestamp": "1374674556", "value":
{"count": 2409}},
{"timestamp": "1371218784", "value":
{"count": 2413}},
{"timestamp": "1360679419", "value":
{"count": 2407}},
{"timestamp": "1365977266", "value":
{"count": 2410}},
{"timestamp": "1362892367", "value":
{"count": 2409}},
{"timestamp": "1375631958", "value":
{"count": 2408}},
{"timestamp": "1365638973", "value":
{"count": 2403}},
{"timestamp": "1371216653", "value":
{"count": 2410}},
{"timestamp": "1372650591", "value":
{"count": 2402}},
{"timestamp": "1367864775", "value":
{"count": 2404}},
{"timestamp": "1358773756", "value":
{"count": 2399}},
{"timestamp": "1367722147", "value":
{"count": 2402}},
{"timestamp": "1367279737", "value":
{"count": 2403}},
{"timestamp": "1364311747", "value":
{"count": 2404}},
{"timestamp": "1363530056", "value":
{"count": 2399}},
{"timestamp": "1360088142", "value":
{"count": 2396}},
{"timestamp": "1349828783", "value":
{"count": 2401}},
{"timestamp": "1362683110", "value":
{"count": 2399}},
{"timestamp": "1356051769", "value":
{"count": 2400}},
{"timestamp": "1366128860", "value":
{"count": 2396}},
{"timestamp": "1374132930", "value":
{"count": 2390}},
{"timestamp": "1359695421", "value":
{"count": 2389}},
{"timestamp": "1352868448", "value":
{"count": 2390}},
{"timestamp": "1365192934", "value":
{"count": 2395}},
{"timestamp": "1354026635", "value":
{"count": 2389}},
{"timestamp": "1360383717", "value":
{"count": 2390}},
{"timestamp": "1370038617", "value":
{"count": 2383}},
{"timestamp": "1369000266", "value":
{"count": 2378}},
{"timestamp": "1351537202", "value":
{"count": 2377}},
{"timestamp": "1373368461", "value":
{"count": 2380}},
{"timestamp": "1361137690", "value":
{"count": 2379}},
{"timestamp": "1344506428", "value":
{"count": 2380}},
{"timestamp": "1375332847", "value":
{"count": 2378}},
{"timestamp": "1353098114", "value":
{"count": 2369}},
{"timestamp": "1370702664", "value":
{"count": 2374}},
{"timestamp": "1373240342", "value":
{"count": 2378}},
{"timestamp": "1371524149", "value":
{"count": 2370}},
{"timestamp": "1369788462", "value":
{"count": 2370}},
{"timestamp": "1371319471", "value":
{"count": 2368}},
{"timestamp": "1341918871", "value":
{"count": 2366}},
{"timestamp": "1364309340", "value":
{"count": 2361}},
{"timestamp": "1371474344", "value":
{"count": 2365}},
{"timestamp": "1366932191", "value":
{"count": 2368}},
{"timestamp": "1365735341", "value":
{"count": 2362}},
{"timestamp": "1352834597", "value":
{"count": 2361}},
{"timestamp": "1363997471", "value":
{"count": 2359}},
{"timestamp": "1365864533", "value":
{"count": 2356}},
{"timestamp": "1373551882", "value":
{"count": 2356}},
{"timestamp": "1375046804", "value":
{"count": 2355}},
{"timestamp": "1357409646", "value":
{"count": 2351}},
{"timestamp": "1353033008", "value":
{"count": 2351}},
{"timestamp": "1375986511", "value":
{"count": 2352}},
{"timestamp": "1369148396", "value":
{"count": 2352}},
{"timestamp": "1369883275", "value":
{"count": 2347}},
{"timestamp": "1367066809", "value":
{"count": 2350}},
{"timestamp": "1371560147", "value":
{"count": 2347}},
{"timestamp": "1368282580", "value":
{"count": 2342}},
{"timestamp": "1347074200", "value":
{"count": 2342}},
{"timestamp": "1367232759", "value":
{"count": 2346}},
{"timestamp": "1357656160", "value":
{"count": 2340}},
{"timestamp": "1363904658", "value":
{"count": 2346}},
{"timestamp": "1361646686", "value":
{"count": 2338}},
{"timestamp": "1374118473", "value":
{"count": 2340}},
{"timestamp": "1355479340", "value":
{"count": 2342}},
{"timestamp": "1359776521", "value":
{"count": 2338}},
{"timestamp": "1371825499", "value":
{"count": 2336}},
{"timestamp": "1371797182", "value":
{"count": 2336}},
{"timestamp": "1366604606", "value":
{"count": 2334}},
{"timestamp": "1369735844", "value":
{"count": 2329}},
{"timestamp": "1361042365", "value":
{"count": 2337}},
{"timestamp": "1357140526", "value":
{"count": 2332}},
{"timestamp": "1349720555", "value":
{"count": 2331}},
{"timestamp": "1366071402", "value":
{"count": 2325}},
{"timestamp": "1362152281", "value":
{"count": 2324}},
{"timestamp": "1376232880", "value":
{"count": 2326}},
{"timestamp": "1373652772", "value":
{"count": 2323}},
{"timestamp": "1370613398", "value":
{"count": 2325}},
{"timestamp": "1372699731", "value":
{"count": 2322}},
{"timestamp": "1369975311", "value":
{"count": 2321}},
{"timestamp": "1353339854", "value":
{"count": 2316}},
{"timestamp": "1373721336", "value":
{"count": 2316}},
{"timestamp": "1368713015", "value":
{"count": 2321}},
{"timestamp": "1352921233", "value":
{"count": 2323}},
{"timestamp": "1366026306", "value":
{"count": 2319}},
{"timestamp": "1364670621", "value":
{"count": 2320}},
{"timestamp": "1369317248", "value":
{"count": 2314}},
{"timestamp": "1376152789", "value":
{"count": 2313}},
{"timestamp": "1367034400", "value":
{"count": 2312}},
{"timestamp": "1375623593", "value":
{"count": 2316}},
{"timestamp": "1358847955", "value":
{"count": 2305}},
{"timestamp": "1347995390", "value":
{"count": 2308}},
{"timestamp": "1361720212", "value":
{"count": 2306}},
{"timestamp": "1370180684", "value":
{"count": 2303}},
{"timestamp": "1368484316", "value":
{"count": 2302}},
{"timestamp": "1365590621", "value":
{"count": 2310}},
{"timestamp": "1370915666", "value":
{"count": 2302}},
{"timestamp": "1356973911", "value":
{"count": 2305}},
{"timestamp": "1351887111", "value":
{"count": 2302}},
{"timestamp": "1345076517", "value":
{"count": 2303}},
{"timestamp": "1356886730", "value":
{"count": 2304}},
{"timestamp": "1375041882", "value":
{"count": 2302}},
{"timestamp": "1362829403", "value":
{"count": 2302}},
{"timestamp": "1360262968", "value":
{"count": 2307}},
{"timestamp": "1363864023", "value":
{"count": 2301}},
{"timestamp": "1369057576", "value":
{"count": 2291}},
{"timestamp": "1350191073", "value":
{"count": 2292}},
{"timestamp": "1366935729", "value":
{"count": 2291}},
{"timestamp": "1355900876", "value":
{"count": 2295}},
{"timestamp": "1366230741", "value":
{"count": 2293}},
{"timestamp": "1374979197", "value":
{"count": 2287}},
{"timestamp": "1355081046", "value":
{"count": 2287}},
{"timestamp": "1374348702", "value":
{"count": 2290}},
{"timestamp": "1369320433", "value":
{"count": 2285}},
{"timestamp": "1369865862", "value":
{"count": 2288}},
{"timestamp": "1360289271", "value":
{"count": 2289}},
{"timestamp": "1374876914", "value":
{"count": 2289}},
{"timestamp": "1370876020", "value":
{"count": 2285}},
{"timestamp": "1367419350", "value":
{"count": 2289}},
{"timestamp": "1352997669", "value":
{"count": 2292}},
{"timestamp": "1370338241", "value":
{"count": 2286}},
{"timestamp": "1366750612", "value":
{"count": 2283}},
{"timestamp": "1373805760", "value":
{"count": 2282}},
{"timestamp": "1372601433", "value":
{"count": 2286}},
{"timestamp": "1358091288", "value":
{"count": 2284}},
{"timestamp": "1369086052", "value":
{"count": 2288}},
{"timestamp": "1360252027", "value":
{"count": 2287}},
{"timestamp": "1374586154", "value":
{"count": 2277}},
{"timestamp": "1363017284", "value":
{"count": 2284}},
{"timestamp": "1362608052", "value":
{"count": 2281}},
{"timestamp": "1353544493", "value":
{"count": 2277}},
{"timestamp": "1347839724", "value":
{"count": 2282}},
{"timestamp": "1368307667", "value":
{"count": 2278}},
{"timestamp": "1353617056", "value":
{"count": 2271}},
{"timestamp": "1347384878", "value":
{"count": 2274}},
{"timestamp": "1368730832", "value":
{"count": 2272}},
{"timestamp": "1363650934", "value":
{"count": 2269}},
{"timestamp": "1367673785", "value":
{"count": 2268}},
{"timestamp": "1374728966", "value":
{"count": 2270}},
{"timestamp": "1366679359", "value":
{"count": 2271}},
{"timestamp": "1373851180", "value":
{"count": 2270}},
{"timestamp": "1356534198", "value":
{"count": 2270}},
{"timestamp": "1361280503", "value":
{"count": 2263}},
{"timestamp": "1353302629", "value":
{"count": 2267}},
{"timestamp": "1373180377", "value":
{"count": 2263}},
{"timestamp": "1356576196", "value":
{"count": 2263}},
{"timestamp": "1370954004", "value":
{"count": 2264}},
{"timestamp": "1375225784", "value":
{"count": 2256}},
{"timestamp": "1361979949", "value":
{"count": 2256}},
{"timestamp": "1352505565", "value":
{"count": 2259}},
{"timestamp": "1355593046", "value":
{"count": 2252}},
{"timestamp": "1373987722", "value":
{"count": 2255}},
{"timestamp": "1370823948", "value":
{"count": 2252}},
{"timestamp": "1359391912", "value":
{"count": 2254}},
{"timestamp": "1367515419", "value":
{"count": 2250}},
{"timestamp": "1370196112", "value":
{"count": 2251}},
{"timestamp": "1375893543", "value":
{"count": 2251}},
{"timestamp": "1374948902", "value":
{"count": 2253}},
{"timestamp": "1351235845", "value":
{"count": 2249}},
{"timestamp": "1361195471", "value":
{"count": 2253}},
{"timestamp": "1360005811", "value":
{"count": 2253}},
{"timestamp": "1376424425", "value":
{"count": 2249}},
{"timestamp": "1375152966", "value":
{"count": 2242}},
{"timestamp": "1370018017", "value":
{"count": 2245}},
{"timestamp": "1354877685", "value":
{"count": 2248}},
{"timestamp": "1369932947", "value":
{"count": 2248}},
{"timestamp": "1352722248", "value":
{"count": 2248}},
{"timestamp": "1372380651", "value":
{"count": 2246}},
{"timestamp": "1363300712", "value":
{"count": 2239}},
{"timestamp": "1367988067", "value":
{"count": 2241}},
{"timestamp": "1364982688", "value":
{"count": 2244}},
{"timestamp": "1364327606", "value":
{"count": 2238}},
{"timestamp": "1375314256", "value":
{"count": 2237}},
{"timestamp": "1373661476", "value":
{"count": 2239}},
{"timestamp": "1369697196", "value":
{"count": 2234}},
{"timestamp": "1353203821", "value":
{"count": 2237}},
{"timestamp": "1364052261", "value":
{"count": 2237}},
{"timestamp": "1360636771", "value":
{"count": 2238}},
{"timestamp": "1369618525", "value":
{"count": 2241}},
{"timestamp": "1362598334", "value":
{"count": 2236}},
{"timestamp": "1358282174", "value":
{"count": 2238}},
{"timestamp": "1371739599", "value":
{"count": 2239}},
{"timestamp": "1353765932", "value":
{"count": 2231}},
{"timestamp": "1369857455", "value":
{"count": 2232}},
{"timestamp": "1368243300", "value":
{"count": 2228}},
{"timestamp": "1367511884", "value":
{"count": 2233}},
{"timestamp": "1371662056", "value":
{"count": 2225}},
{"timestamp": "1348883260", "value":
{"count": 2226}},
{"timestamp": "1368635453", "value":
{"count": 2228}},
{"timestamp": "1360013780", "value":
{"count": 2227}},
{"timestamp": "1344948357", "value":
{"count": 2222}},
{"timestamp": "1344851643", "value":
{"count": 2224}},
{"timestamp": "1374172259", "value":
{"count": 2224}},
{"timestamp": "1372875113", "value":
{"count": 2227}},
{"timestamp": "1369347359", "value":
{"count": 2229}},
{"timestamp": "1349150612", "value":
{"count": 2224}},
{"timestamp": "1361319918", "value":
{"count": 2219}},
{"timestamp": "1359060351", "value":
{"count": 2219}},
{"timestamp": "1359924850", "value":
{"count": 2215}},
{"timestamp": "1359113707", "value":
{"count": 2215}},
{"timestamp": "1371153095", "value":
{"count": 2216}},
{"timestamp": "1370988093", "value":
{"count": 2215}},
{"timestamp": "1371610211", "value":
{"count": 2215}},
{"timestamp": "1367681175", "value":
{"count": 2206}},
{"timestamp": "1357349799", "value":
{"count": 2212}},
{"timestamp": "1371953515", "value":
{"count": 2213}},
{"timestamp": "1363745102", "value":
{"count": 2206}},
{"timestamp": "1369103685", "value":
{"count": 2206}},
{"timestamp": "1368097119", "value":
{"count": 2209}},
{"timestamp": "1362110162", "value":
{"count": 2204}},
{"timestamp": "1348468598", "value":
{"count": 2205}},
{"timestamp": "1361975070", "value":
{"count": 2200}},
{"timestamp": "1348838693", "value":
{"count": 2204}},
{"timestamp": "1363485446", "value":
{"count": 2201}},
{"timestamp": "1358860958", "value":
{"count": 2195}},
{"timestamp": "1345133240", "value":
{"count": 2202}},
{"timestamp": "1369422268", "value":
{"count": 2208}},
{"timestamp": "1375149326", "value":
{"count": 2199}},
{"timestamp": "1372123232", "value":
{"count": 2194}},
{"timestamp": "1348266612", "value":
{"count": 2196}},
{"timestamp": "1359485240", "value":
{"count": 2201}},
{"timestamp": "1352305448", "value":
{"count": 2201}},
{"timestamp": "1351721563", "value":
{"count": 2191}},
{"timestamp": "1350375878", "value":
{"count": 2200}},
{"timestamp": "1360704393", "value":
{"count": 2201}},
{"timestamp": "1355759068", "value":
{"count": 2193}},
{"timestamp": "1366838773", "value":
{"count": 2195}},
{"timestamp": "1348537058", "value":
{"count": 2199}},
{"timestamp": "1373038365", "value":
{"count": 2189}},
{"timestamp": "1357523702", "value":
{"count": 2192}},
{"timestamp": "1362615504", "value":
{"count": 2189}},
{"timestamp": "1362212408", "value":
{"count": 2187}},
{"timestamp": "1355324033", "value":
{"count": 2187}},
{"timestamp": "1365520094", "value":
{"count": 2185}},
{"timestamp": "1370713610", "value":
{"count": 2184}},
{"timestamp": "1370464352", "value":
{"count": 2186}},
{"timestamp": "1353410888", "value":
{"count": 2180}},
{"timestamp": "1373765675", "value":
{"count": 2175}},
{"timestamp": "1364421046", "value":
{"count": 2176}},
{"timestamp": "1354357792", "value":
{"count": 2183}},
{"timestamp": "1371328061", "value":
{"count": 2175}},
{"timestamp": "1354666704", "value":
{"count": 2176}},
{"timestamp": "1350708453", "value":
{"count": 2175}},
{"timestamp": "1358976397", "value":
{"count": 2173}},
{"timestamp": "1358695079", "value":
{"count": 2174}},
{"timestamp": "1372007060", "value":
{"count": 2175}},
{"timestamp": "1369184084", "value":
{"count": 2169}},
{"timestamp": "1366764625", "value":
{"count": 2172}},
{"timestamp": "1365431238", "value":
{"count": 2172}},
{"timestamp": "1372900592", "value":
{"count": 2169}},
{"timestamp": "1360334854", "value":
{"count": 2164}},
{"timestamp": "1369954159", "value":
{"count": 2170}},
{"timestamp": "1368445859", "value":
{"count": 2165}},
{"timestamp": "1361722852", "value":
{"count": 2161}},
{"timestamp": "1376270122", "value":
{"count": 2161}},
{"timestamp": "1373391438", "value":
{"count": 2161}},
{"timestamp": "1372630910", "value":
{"count": 2158}},
{"timestamp": "1371335052", "value":
{"count": 2160}},
{"timestamp": "1366393484", "value":
{"count": 2162}},
{"timestamp": "1372773739", "value":
{"count": 2158}},
{"timestamp": "1370302068", "value":
{"count": 2160}},
{"timestamp": "1371911519", "value":
{"count": 2156}},
{"timestamp": "1375182274", "value":
{"count": 2151}},
{"timestamp": "1366582838", "value":
{"count": 2154}},
{"timestamp": "1365621031", "value":
{"count": 2150}},
{"timestamp": "1358470318", "value":
{"count": 2153}},
{"timestamp": "1351688962", "value":
{"count": 2149}},
{"timestamp": "1373637125", "value":
{"count": 2155}},
{"timestamp": "1370369847", "value":
{"count": 2148}},
{"timestamp": "1358927756", "value":
{"count": 2155}},
{"timestamp": "1357491323", "value":
{"count": 2153}},
{"timestamp": "1353109900", "value":
{"count": 2152}},
{"timestamp": "1365710148", "value":
{"count": 2146}},
{"timestamp": "1366977792", "value":
{"count": 2146}},
{"timestamp": "1365277823", "value":
{"count": 2142}},
{"timestamp": "1366325121", "value":
{"count": 2143}},
{"timestamp": "1371716907", "value":
{"count": 2141}},
{"timestamp": "1370271556", "value":
{"count": 2142}},
{"timestamp": "1359762792", "value":
{"count": 2139}},
{"timestamp": "1356544693", "value":
{"count": 2143}},
{"timestamp": "1348934673", "value":
{"count": 2145}},
{"timestamp": "1348753321", "value":
{"count": 2140}},
{"timestamp": "1364752989", "value":
{"count": 2139}},
{"timestamp": "1362070254", "value":
{"count": 2138}},
{"timestamp": "1361929450", "value":
{"count": 2132}},
{"timestamp": "1349708198", "value":
{"count": 2138}},
{"timestamp": "1374322597", "value":
{"count": 2136}},
{"timestamp": "1373333850", "value":
{"count": 2133}},
{"timestamp": "1372974357", "value":
{"count": 2136}},
{"timestamp": "1368993930", "value":
{"count": 2128}},
{"timestamp": "1349608665", "value":
{"count": 2136}},
{"timestamp": "1375112231", "value":
{"count": 2134}},
{"timestamp": "1363350575", "value":
{"count": 2130}},
{"timestamp": "1356347144", "value":
{"count": 2131}},
{"timestamp": "1365449014", "value":
{"count": 2127}},
{"timestamp": "1367683038", "value":
{"count": 2128}},
{"timestamp": "1357625429", "value":
{"count": 2123}},
{"timestamp": "1375108088", "value":
{"count": 2126}},
{"timestamp": "1367850278", "value":
{"count": 2125}},
{"timestamp": "1356216800", "value":
{"count": 2122}},
{"timestamp": "1368658047", "value":
{"count": 2125}},
{"timestamp": "1350500334", "value":
{"count": 2120}},
{"timestamp": "1353857679", "value":
{"count": 2123}},
{"timestamp": "1361803538", "value":
{"count": 2118}},
{"timestamp": "1352466595", "value":
{"count": 2122}},
{"timestamp": "1374174798", "value":
{"count": 2123}},
{"timestamp": "1370975565", "value":
{"count": 2112}},
{"timestamp": "1359243954", "value":
{"count": 2113}},
{"timestamp": "1351771468", "value":
{"count": 2117}},
{"timestamp": "1376415278", "value":
{"count": 2114}},
{"timestamp": "1376570245", "value":
{"count": 2112}},
{"timestamp": "1362782897", "value":
{"count": 2109}},
{"timestamp": "1366895668", "value":
{"count": 2108}},
{"timestamp": "1361232188", "value":
{"count": 2104}},
{"timestamp": "1371771020", "value":
{"count": 2098}},
{"timestamp": "1367513078", "value":
{"count": 2107}},
{"timestamp": "1370194548", "value":
{"count": 2105}},
{"timestamp": "1363476008", "value":
{"count": 2098}},
{"timestamp": "1360711077", "value":
{"count": 2103}},
{"timestamp": "1375491146", "value":
{"count": 2105}},
{"timestamp": "1357877864", "value":
{"count": 2101}},
{"timestamp": "1376418683", "value":
{"count": 2100}},
{"timestamp": "1374150006", "value":
{"count": 2096}},
{"timestamp": "1368199809", "value":
{"count": 2093}},
{"timestamp": "1366404749", "value":
{"count": 2093}},
{"timestamp": "1364305264", "value":
{"count": 2096}},
{"timestamp": "1347282438", "value":
{"count": 2093}},
{"timestamp": "1365384174", "value":
{"count": 2096}},
{"timestamp": "1370226390", "value":
{"count": 2096}},
{"timestamp": "1362223198", "value":
{"count": 2090}},
{"timestamp": "1369588127", "value":
{"count": 2089}},
{"timestamp": "1366417863", "value":
{"count": 2089}},
{"timestamp": "1363303454", "value":
{"count": 2091}},
{"timestamp": "1359985374", "value":
{"count": 2085}},
{"timestamp": "1352827024", "value":
{"count": 2084}},
{"timestamp": "1360764467", "value":
{"count": 2079}},
{"timestamp": "1347458626", "value":
{"count": 2079}},
{"timestamp": "1361126188", "value":
{"count": 2087}},
{"timestamp": "1372124310", "value":
{"count": 2083}},
{"timestamp": "1365550180", "value":
{"count": 2076}},
{"timestamp": "1365087987", "value":
{"count": 2082}},
{"timestamp": "1373829268", "value":
{"count": 2076}},
{"timestamp": "1375960133", "value":
{"count": 2080}},
{"timestamp": "1374900481", "value":
{"count": 2074}},
{"timestamp": "1345387269", "value":
{"count": 2073}},
{"timestamp": "1374086057", "value":
{"count": 2075}},
{"timestamp": "1371357981", "value":
{"count": 2066}},
{"timestamp": "1349139012", "value":
{"count": 2068}},
{"timestamp": "1369913652", "value":
{"count": 2064}},
{"timestamp": "1366134953", "value":
{"count": 2064}},
{"timestamp": "1361220993", "value":
{"count": 2062}},
{"timestamp": "1350946732", "value":
{"count": 2065}},
{"timestamp": "1369513405", "value":
{"count": 2065}},
{"timestamp": "1363448379", "value":
{"count": 2066}},
{"timestamp": "1367498602", "value":
{"count": 2061}},
{"timestamp": "1353867238", "value":
{"count": 2059}},
{"timestamp": "1348849570", "value":
{"count": 2053}},
{"timestamp": "1371074043", "value":
{"count": 2059}},
{"timestamp": "1361065907", "value":
{"count": 2061}},
{"timestamp": "1359855288", "value":
{"count": 2059}},
{"timestamp": "1371092735", "value":
{"count": 2054}},
{"timestamp": "1372560268", "value":
{"count": 2053}},
{"timestamp": "1367672799", "value":
{"count": 2050}},
{"timestamp": "1358185715", "value":
{"count": 2053}},
{"timestamp": "1353200899", "value":
{"count": 2059}},
{"timestamp": "1342310838", "value":
{"count": 2057}},
{"timestamp": "1369489283", "value":
{"count": 2058}},
{"timestamp": "1352137083", "value":
{"count": 2051}},
{"timestamp": "1349361279", "value":
{"count": 2043}},
{"timestamp": "1355365316", "value":
{"count": 2047}},
{"timestamp": "1373477565", "value":
{"count": 2048}},
{"timestamp": "1373243178", "value":
{"count": 2043}},
{"timestamp": "1369840927", "value":
{"count": 2046}},
{"timestamp": "1354216589", "value":
{"count": 2039}},
{"timestamp": "1373889863", "value":
{"count": 2041}},
{"timestamp": "1365522582", "value":
{"count": 2039}},
{"timestamp": "1372926553", "value":
{"count": 2040}},
{"timestamp": "1375018432", "value":
{"count": 2042}},
{"timestamp": "1363276678", "value":
{"count": 2039}},
{"timestamp": "1351742370", "value":
{"count": 2041}},
{"timestamp": "1357833730", "value":
{"count": 2034}},
{"timestamp": "1343924479", "value":
{"count": 2038}},
{"timestamp": "1366669473", "value":
{"count": 2033}},
{"timestamp": "1366550166", "value":
{"count": 2033}},
{"timestamp": "1362578577", "value":
{"count": 2028}},
{"timestamp": "1372741783", "value":
{"count": 2025}},
{"timestamp": "1371663758", "value":
{"count": 2019}},
{"timestamp": "1366406686", "value":
{"count": 2024}},
{"timestamp": "1353163211", "value":
{"count": 2028}},
{"timestamp": "1375646346", "value":
{"count": 2024}},
{"timestamp": "1370548912", "value":
{"count": 2023}},
{"timestamp": "1366814897", "value":
{"count": 2020}},
{"timestamp": "1352925100", "value":
{"count": 2015}},
{"timestamp": "1363830800", "value":
{"count": 2024}},
{"timestamp": "1373122338", "value":
{"count": 2014}},
{"timestamp": "1360445183", "value":
{"count": 2020}},
{"timestamp": "1361540142", "value":
{"count": 2021}},
{"timestamp": "1373074249", "value":
{"count": 2018}},
{"timestamp": "1359200174", "value":
{"count": 2013}},
{"timestamp": "1345917284", "value":
{"count": 2015}},
{"timestamp": "1354468958", "value":
{"count": 2012}},
{"timestamp": "1373334389", "value":
{"count": 2014}},
{"timestamp": "1368826583", "value":
{"count": 2006}},
{"timestamp": "1363211232", "value":
{"count": 2006}},
{"timestamp": "1356568661", "value":
{"count": 2011}},
{"timestamp": "1360246861", "value":
{"count": 2006}},
{"timestamp": "1357855957", "value":
{"count": 2008}},
{"timestamp": "1375194482", "value":
{"count": 2005}},
{"timestamp": "1363790988", "value":
{"count": 2000}},
{"timestamp": "1339698523", "value":
{"count": 2007}},
{"timestamp": "1370868616", "value":
{"count": 1998}},
{"timestamp": "1366553413", "value":
{"count": 1992}},
{"timestamp": "1376583685", "value":
{"count": 2003}},
{"timestamp": "1353464042", "value":
{"count": 1998}},
{"timestamp": "1376355865", "value":
{"count": 1990}},
{"timestamp": "1353622152", "value":
{"count": 1999}},
{"timestamp": "1365085088", "value":
{"count": 1994}},
{"timestamp": "1358899898", "value":
{"count": 1985}},
{"timestamp": "1372291212", "value":
{"count": 1991}},
{"timestamp": "1364848712", "value":
{"count": 1987}},
{"timestamp": "1372975149", "value":
{"count": 1989}},
{"timestamp": "1358681996", "value":
{"count": 1979}},
{"timestamp": "1349262210", "value":
{"count": 1984}},
{"timestamp": "1368639316", "value":
{"count": 1981}},
{"timestamp": "1371494085", "value":
{"count": 1977}},
{"timestamp": "1359581993", "value":
{"count": 1980}},
{"timestamp": "1375888075", "value":
{"count": 1980}},
{"timestamp": "1361908058", "value":
{"count": 1976}},
{"timestamp": "1359012221", "value":
{"count": 1972}},
{"timestamp": "1373292683", "value":
{"count": 1976}},
{"timestamp": "1356368608", "value":
{"count": 1978}},
{"timestamp": "1364486231", "value":
{"count": 1975}},
{"timestamp": "1365628464", "value":
{"count": 1972}},
{"timestamp": "1357120004", "value":
{"count": 1977}},
{"timestamp": "1356285015", "value":
{"count": 1974}},
{"timestamp": "1343872284", "value":
{"count": 1971}},
{"timestamp": "1371309258", "value":
{"count": 1971}},
{"timestamp": "1367236122", "value":
{"count": 1967}},
{"timestamp": "1369336434", "value":
{"count": 1968}},
{"timestamp": "1350482813", "value":
{"count": 1963}},
{"timestamp": "1358352481", "value":
{"count": 1971}},
{"timestamp": "1349445830", "value":
{"count": 1960}},
{"timestamp": "1367871572", "value":
{"count": 1957}},
{"timestamp": "1372441178", "value":
{"count": 1953}},
{"timestamp": "1354459594", "value":
{"count": 1962}},
{"timestamp": "1351022653", "value":
{"count": 1959}},
{"timestamp": "1374883026", "value":
{"count": 1953}},
{"timestamp": "1360857096", "value":
{"count": 1954}},
{"timestamp": "1375367440", "value":
{"count": 1949}},
{"timestamp": "1370485834", "value":
{"count": 1939}},
{"timestamp": "1360353451", "value":
{"count": 1943}},
{"timestamp": "1370182410", "value":
{"count": 1939}},
{"timestamp": "1350837046", "value":
{"count": 1940}},
{"timestamp": "1375857813", "value":
{"count": 1939}},
{"timestamp": "1363579268", "value":
{"count": 1939}},
{"timestamp": "1359463331", "value":
{"count": 1940}},
{"timestamp": "1364334520", "value":
{"count": 1941}},
{"timestamp": "1363996555", "value":
{"count": 1939}},
{"timestamp": "1354266893", "value":
{"count": 1940}},
{"timestamp": "1368208605", "value":
{"count": 1939}},
{"timestamp": "1365033223", "value":
{"count": 1940}},
{"timestamp": "1372968957", "value":
{"count": 1938}},
{"timestamp": "1351189188", "value":
{"count": 1939}},
{"timestamp": "1366145764", "value":
{"count": 1930}},
{"timestamp": "1364327521", "value":
{"count": 1931}},
{"timestamp": "1365644058", "value":
{"count": 1930}},
{"timestamp": "1372943731", "value":
{"count": 1931}},
{"timestamp": "1370115223", "value":
{"count": 1929}},
{"timestamp": "1354376457", "value":
{"count": 1927}},
{"timestamp": "1370215573", "value":
{"count": 1932}},
{"timestamp": "1346361730", "value":
{"count": 1928}},
{"timestamp": "1372446355", "value":
{"count": 1922}},
{"timestamp": "1370170436", "value":
{"count": 1923}},
{"timestamp": "1349778830", "value":
{"count": 1925}},
{"timestamp": "1367461370", "value":
{"count": 1924}},
{"timestamp": "1368551039", "value":
{"count": 1926}},
{"timestamp": "1356828470", "value":
{"count": 1916}},
{"timestamp": "1376315762", "value":
{"count": 1915}},
{"timestamp": "1371145477", "value":
{"count": 1915}},
{"timestamp": "1366931490", "value":
{"count": 1923}},
{"timestamp": "1363225876", "value":
{"count": 1920}},
{"timestamp": "1368365828", "value":
{"count": 1912}},
{"timestamp": "1365179295", "value":
{"count": 1911}},
{"timestamp": "1375540521", "value":
{"count": 1913}},
{"timestamp": "1364088058", "value":
{"count": 1915}},
{"timestamp": "1374440300", "value":
{"count": 1905}},
{"timestamp": "1369664723", "value":
{"count": 1911}},
{"timestamp": "1363192103", "value":
{"count": 1912}},
{"timestamp": "1375036876", "value":
{"count": 1903}},
{"timestamp": "1364213919", "value":
{"count": 1903}},
{"timestamp": "1363184922", "value":
{"count": 1906}},
{"timestamp": "1356269251", "value":
{"count": 1905}},
{"timestamp": "1343752872", "value":
{"count": 1904}},
{"timestamp": "1374254682", "value":
{"count": 1900}},
{"timestamp": "1370881309", "value":
{"count": 1906}},
{"timestamp": "1371219518", "value":
{"count": 1898}},
{"timestamp": "1347637039", "value":
{"count": 1899}},
{"timestamp": "1367974344", "value":
{"count": 1904}},
{"timestamp": "1346532848", "value":
{"count": 1896}},
{"timestamp": "1365624999", "value":
{"count": 1895}},
{"timestamp": "1358526201", "value":
{"count": 1894}},
{"timestamp": "1366980243", "value":
{"count": 1897}},
{"timestamp": "1366385040", "value":
{"count": 1901}},
{"timestamp": "1362014084", "value":
{"count": 1895}},
{"timestamp": "1360428816", "value":
{"count": 1899}},
{"timestamp": "1351628921", "value":
{"count": 1898}},
{"timestamp": "1349023953", "value":
{"count": 1893}},
{"timestamp": "1360262112", "value":
{"count": 1899}},
{"timestamp": "1349097843", "value":
{"count": 1896}},
{"timestamp": "1370209378", "value":
{"count": 1896}},
{"timestamp": "1365256143", "value":
{"count": 1890}},
{"timestamp": "1358880143", "value":
{"count": 1893}},
{"timestamp": "1371327043", "value":
{"count": 1889}},
{"timestamp": "1364480684", "value":
{"count": 1886}},
{"timestamp": "1360794683", "value":
{"count": 1887}},
{"timestamp": "1372700335", "value":
{"count": 1882}},
{"timestamp": "1364814703", "value":
{"count": 1886}},
{"timestamp": "1355326414", "value":
{"count": 1879}},
{"timestamp": "1339002701", "value":
{"count": 1879}},
{"timestamp": "1351435252", "value":
{"count": 1881}},
{"timestamp": "1353864025", "value":
{"count": 1878}},
{"timestamp": "1371176717", "value":
{"count": 1876}},
{"timestamp": "1358999496", "value":
{"count": 1878}},
{"timestamp": "1357320047", "value":
{"count": 1880}},
{"timestamp": "1349963526", "value":
{"count": 1879}},
{"timestamp": "1366206928", "value":
{"count": 1880}},
{"timestamp": "1355861242", "value":
{"count": 1880}},
{"timestamp": "1368977827", "value":
{"count": 1877}},
{"timestamp": "1356698737", "value":
{"count": 1876}},
{"timestamp": "1374487952", "value":
{"count": 1874}},
{"timestamp": "1361119723", "value":
{"count": 1872}},
{"timestamp": "1356714676", "value":
{"count": 1874}},
{"timestamp": "1348584317", "value":
{"count": 1877}},
{"timestamp": "1355843800", "value":
{"count": 1868}},
{"timestamp": "1375987336", "value":
{"count": 1869}},
{"timestamp": "1369689517", "value":
{"count": 1868}},
{"timestamp": "1351005036", "value":
{"count": 1870}},
{"timestamp": "1358260169", "value":
{"count": 1864}},
{"timestamp": "1364493670", "value":
{"count": 1863}},
{"timestamp": "1372186458", "value":
{"count": 1859}},
{"timestamp": "1372184499", "value":
{"count": 1865}},
{"timestamp": "1363709613", "value":
{"count": 1856}},
{"timestamp": "1364902361", "value":
{"count": 1856}},
{"timestamp": "1355685671", "value":
{"count": 1853}},
{"timestamp": "1370927616", "value":
{"count": 1857}},
{"timestamp": "1361766040", "value":
{"count": 1855}},
{"timestamp": "1364419236", "value":
{"count": 1850}},
{"timestamp": "1361463375", "value":
{"count": 1852}},
{"timestamp": "1367423803", "value":
{"count": 1850}},
{"timestamp": "1369785249", "value":
{"count": 1853}},
{"timestamp": "1350431224", "value":
{"count": 1850}},
{"timestamp": "1364775436", "value":
{"count": 1845}},
{"timestamp": "1357837565", "value":
{"count": 1849}},
{"timestamp": "1357561761", "value":
{"count": 1842}},
{"timestamp": "1349036337", "value":
{"count": 1851}},
{"timestamp": "1366420790", "value":
{"count": 1846}},
{"timestamp": "1363022285", "value":
{"count": 1848}}]
}